[{"Name":"Quarterly Business Review - Q2FY22","Type":0,"Viewed":false,"Artifacts":[{"Name":"Presentation #1","Type":3,"Size":10031,"Tags":{"cool":"maybe"}},{"Name":"Sales #1","Type":2,"Size":100310,"Tags":{"confidential":"yes"}}],"Tags":{"cool":"super"},"Authors":["Alex","Todd"],"JustForFun":[1,2,3]},{"Name":"Other","Type":0,"Viewed":false,"Artifacts":[{"Name":"Presentation #1","Type":3,"Size":10031,"Tags":{"cool":"maybe"}},{"Name":"Sales #1","Type":2,"Size":100310,"Tags":{"confidential":"yes"}}],"Tags":{"cool":"super"},"Authors":["Alex","Todd"],"JustForFun":[1,2,3]},{"Name":"Again","Type":0,"Viewed":false,"Artifacts":[{"Name":"Presentation #1","Type":3,"Size":10031,"Tags":{"cool":"maybe"}},{"Name":"Sales #1","Type":2,"Size":100310,"Tags":{"confidential":"yes"}}],"Tags":{"cool":"super"},"Authors":["Alex","Todd"]}]
